{"id": "fd_insecticidal_gas", "fg": [{"weight": 10, "sprite": "10836_fd_insecticidal_gas_0"}, {"weight": 10, "sprite": "10838_fd_insecticidal_gas_1"}, {"weight": 10, "sprite": "10839_fd_insecticidal_gas_2"}, {"weight": 10, "sprite": "10840_fd_insecticidal_gas_3"}, {"weight": 10, "sprite": "10841_fd_insecticidal_gas_4"}, {"weight": 10, "sprite": "10842_fd_insecticidal_gas_5"}, {"weight": 10, "sprite": "10843_fd_insecticidal_gas_6"}, {"weight": 10, "sprite": "10844_fd_insecticidal_gas_7"}, {"weight": 10, "sprite": "10845_fd_insecticidal_gas_8"}, {"weight": 10, "sprite": "10837_fd_insecticidal_gas_9"}], "animated": true, "bg": []}