[{"type": "mod_tileset", "compatibility": ["UNDEAD_PEOPLE_BASE", "UNDEAD_PEOPLE", "MshockXottoplus", "UNDEAD_PEOPLE_LIGHT", "MSX++DEAD_PEOPLE"], "tiles-new": [{"file": "secronom_normal.png", "tiles": [{"id": "bg_dirt", "fg": 1}, {"id": "bg_dirt_season_winter", "fg": 2, "rotates": false}, {"id": "bg_dirt_vector_season_winter", "fg": 3, "rotates": false}, {"id": "bg_flesh_rock_floor", "fg": 4, "rotates": false}, {"id": "bg_pavement", "fg": 5, "rotates": false}, {"id": "bg_shaddow_custom1", "fg": 6, "rotates": false}, {"id": "bg_shaddow_custom5", "fg": 7, "rotates": false}, {"id": "bg_shaddow_custom6", "fg": 8, "rotates": false}, {"id": "bg_shadow_normal", "fg": 9}, {"id": "hatchingsaddleregg", "fg": 10}, {"id": "saddler_egg", "fg": 11}, {"id": "saddler_egg_hatched", "fg": 12}, {"id": "secro_flesh", "fg": [{"weight": 30, "sprite": 13}, {"weight": 30, "sprite": 14}, {"weight": 30, "sprite": 15}, {"weight": 30, "sprite": 16}], "animated": true}, {"id": ["secro_recipe_flesh"], "fg": 17}, {"id": ["secro_recipe_flesh_field"], "fg": 18}, {"id": "cheytac", "fg": 19}, {"id": "overlay_wielded_cheytac", "fg": 20}, {"id": "cheytacmag", "fg": 21}, {"id": "hecate", "fg": 22}, {"id": "overlay_wielded_hecate", "fg": 23}, {"id": "hecatemag", "fg": 24}, {"id": "hecate_muzzle_brake", "fg": 25}, {"id": "kacc", "fg": 26}, {"id": "overlay_wielded_kacc", "fg": 27}, {"id": "laser_rifle_secro", "fg": 28}, {"id": "overlay_wielded_laser_rifle_secro", "fg": 29}, {"id": "psg1", "fg": 30}, {"id": "overlay_wielded_psg1", "fg": 31}, {"id": "SS_grenade_launcher", "fg": 32}, {"id": "overlay_wielded_SS_grenade_launcher", "fg": 33}, {"id": "walther2000", "fg": 34}, {"id": "overlay_wielded_walther2000", "fg": 35}, {"id": "walther2000mag", "fg": 36}, {"id": "xm556", "fg": 37}, {"id": "overlay_wielded_xm556", "fg": 38}, {"id": "xm8", "fg": 39}, {"id": "overlay_wielded_xm8", "fg": 40}, {"id": "fd_blood_acid", "fg": 41, "rotates": true, "multitile": true, "additional_tiles": [{"id": "center", "fg": 42}, {"id": "corner", "fg": [43, 44, 45, 46]}, {"id": "t_connection", "fg": [53, 54, 55, 56]}, {"id": "edge", "fg": [47, 48]}, {"id": "end_piece", "fg": [49, 50, 51, 52]}, {"id": "unconnected", "fg": 57}]}, {"id": "fd_charger_stun", "fg": 58}, {"id": "fd_cordev_corrupt_acid", "fg": 59, "rotates": true, "multitile": true, "additional_tiles": [{"id": "center", "fg": 60}, {"id": "corner", "fg": [61, 62, 63, 64]}, {"id": "t_connection", "fg": [71, 72, 73, 74]}, {"id": "edge", "fg": [65, 66]}, {"id": "end_piece", "fg": [67, 68, 69, 70]}, {"id": "unconnected", "fg": 75}]}, {"id": "fd_disser_scream", "fg": 76}, {"id": "fd_equinox_flesh", "fg": 77, "rotates": true, "multitile": true, "additional_tiles": [{"id": "center", "fg": 78}, {"id": "corner", "fg": [79, 80, 81, 82]}, {"id": "t_connection", "fg": [89, 90, 91, 92]}, {"id": "edge", "fg": [83, 84]}, {"id": "end_piece", "fg": [85, 86, 87, 88]}, {"id": "unconnected", "fg": 93}]}, {"id": "fd_fleshknot_gas", "fg": 94}, {"id": "fd_flesh_biome", "fg": 95}, {"id": "fd_flesh_biome_immune", "fg": 96}, {"id": "fd_flesh_tree_grab", "fg": 97}, {"id": "fd_gorepit_center", "fg": 98}, {"id": "fd_gorepit_combat", "fg": 99}, {"id": "fd_gorepit_normal", "fg": 100}, {"id": "fd_gorepit_wall", "fg": 101, "rotates": true, "multitile": true, "additional_tiles": [{"id": "center", "fg": 102}, {"id": "corner", "fg": [103, 104, 105, 106]}, {"id": "t_connection", "fg": [113, 114, 115, 116]}, {"id": "edge", "fg": [107, 108]}, {"id": "end_piece", "fg": [109, 110, 111, 112]}, {"id": "unconnected", "fg": 117}]}, {"id": "fd_jolt_elec", "fg": 118}, {"id": "fd_mawy_web", "fg": 119, "rotates": true, "multitile": true, "additional_tiles": [{"id": "center", "fg": 120}, {"id": "corner", "fg": [121, 122, 123, 124]}, {"id": "t_connection", "fg": [131, 132, 133, 134]}, {"id": "edge", "fg": [125, 126]}, {"id": "end_piece", "fg": [127, 128, 129, 130]}, {"id": "unconnected", "fg": 135}]}, {"id": "fd_mawy_web_immune", "fg": 136}, {"id": "fd_ministars", "fg": 137}, {"id": "fd_mon_down_immune", "fg": 138}, {"id": "fd_mon_pet", "fg": 139}, {"id": "fd_necros_para_gas", "fg": 140, "rotates": true, "multitile": true, "additional_tiles": [{"id": "center", "fg": 141}, {"id": "corner", "fg": [142, 143, 144, 145]}, {"id": "t_connection", "fg": [152, 153, 154, 155]}, {"id": "edge", "fg": [146, 147]}, {"id": "end_piece", "fg": [148, 149, 150, 151]}, {"id": "unconnected", "fg": 156}]}, {"id": "fd_nix_fear", "fg": 157}, {"id": "fd_portal_carrion", "fg": 158}, {"id": "fd_portal_vector", "fg": 159}, {"id": "fd_relinquished_revive", "fg": 160}, {"id": "fd_resolute_growth", "fg": 161}, {"id": "fd_revenant_allure_induce_immune", "fg": 162}, {"id": "fd_revenant_trigger_immune", "fg": 163}, {"id": "fd_saddler_brute_detach", "fg": 164}, {"id": "fd_saddler_detach", "fg": 165}, {"id": "fd_saddler_scout_detach", "fg": 166}, {"id": "fd_secro_power_armor_flesh_link", "fg": 167}, {"id": "fd_sflesh_bones", "fg": 168}, {"id": "fd_sflesh_fleshling", "fg": 169}, {"id": "fd_sflesh_gas", "fg": 170, "rotates": true, "multitile": true, "additional_tiles": [{"id": "center", "fg": 171}, {"id": "corner", "fg": [172, 173, 174, 175]}, {"id": "t_connection", "fg": [182, 183, 184, 185]}, {"id": "edge", "fg": [176, 177]}, {"id": "end_piece", "fg": [178, 179, 180, 181]}, {"id": "unconnected", "fg": 186}]}, {"id": "fd_sflesh_heap_death", "fg": 187}, {"id": "fd_sflesh_sack", "fg": 188}, {"id": "fd_sflesh_sack_dead", "fg": 189}, {"id": "fd_sflesh_sack_maybe", "fg": 190}, {"id": "fd_sflesh_spawn_jaw", "fg": 191}, {"id": "fd_sflesh_spawn_tendril", "fg": 192}, {"id": "fd_sflesh_taken", "fg": 193}, {"id": "fd_sflesh_tendrils", "fg": 194}, {"id": "fd_sflesh_tentclus", "fg": 195}, {"id": "fd_sflesh_veinstalk_crawler", "fg": 196}, {"id": "fd_sflesh_veinstalk_limiter", "fg": 197}, {"id": "fd_sflesh_veinstalk_popup", "fg": 198}, {"id": "fd_sflesh_wall", "fg": 199}, {"id": "fd_sflesh_wall_limit", "fg": 200}, {"id": "fd_shifter_illu_limiter", "fg": 201}, {"id": "fd_shifter_shift", "fg": 202, "bg": 9}, {"id": "fd_uruxis_combat", "fg": 203}, {"id": "fd_uruxis_normal", "fg": 204}, {"id": "fd_vector_haze", "fg": 205, "rotates": true, "multitile": true, "additional_tiles": [{"id": "center", "fg": 206}, {"id": "corner", "fg": [207, 208, 209, 210]}, {"id": "t_connection", "fg": [217, 218, 219, 220]}, {"id": "edge", "fg": [211, 212]}, {"id": "end_piece", "fg": [213, 214, 215, 216]}, {"id": "unconnected", "fg": 221}]}, {"id": "fd_vector_seed", "fg": 222}, {"id": "f_floral_vector", "fg": 223}, {"id": "t_secro_metal_hatch_c", "fg": 224}, {"id": "t_secro_ramp_down", "fg": 225}, {"id": "t_secro_ramp_up", "fg": 226}, {"id": "t_shrub_vector", "fg": 227, "bg": 231}, {"id": "t_shrub_vector_season_winter", "fg": 228, "bg": 3}, {"id": "t_tree_vector_young", "fg": 229, "bg": 231}, {"id": "t_tree_vector_young_season_winter", "fg": 230, "bg": 2}, {"id": "t_vector", "fg": 231, "rotates": true, "multitile": true, "additional_tiles": [{"id": "center", "fg": 232}, {"id": "corner", "fg": [233, 234, 235, 236]}, {"id": "t_connection", "fg": [243, 244, 245, 246]}, {"id": "edge", "fg": [237, 238]}, {"id": "end_piece", "fg": [239, 240, 241, 242]}, {"id": "unconnected", "fg": 247}]}, {"id": "t_vector_season_winter", "fg": 248, "bg": 2, "rotates": true, "multitile": true, "additional_tiles": [{"id": "center", "fg": 249, "bg": 2}, {"id": "corner", "fg": [250, 251, 252, 253], "bg": 2}, {"id": "t_connection", "fg": [260, 261, 262, 263], "bg": 2}, {"id": "edge", "fg": [254, 255], "bg": 2}, {"id": "end_piece", "fg": [256, 257, 258, 259], "bg": 2}, {"id": "unconnected", "fg": 264, "bg": 2}]}, {"id": "f_secro_biome", "fg": 265, "rotates": true, "multitile": true, "additional_tiles": [{"id": "center", "fg": 266}, {"id": "corner", "fg": [267, 268, 269, 270]}, {"id": "t_connection", "fg": [277, 278, 279, 280]}, {"id": "edge", "fg": [271, 272]}, {"id": "end_piece", "fg": [273, 274, 275, 276]}, {"id": "unconnected", "fg": 281}]}, {"id": "f_secro_boulder_medium_flesh", "fg": 282, "bg": 9}, {"id": "f_secro_boulder_small_flesh", "fg": 283}, {"id": "f_secro_flesh", "fg": 284, "rotates": true, "multitile": true, "additional_tiles": [{"id": "center", "fg": 285}, {"id": "corner", "fg": [286, 287, 288, 289]}, {"id": "t_connection", "fg": [296, 297, 298, 299]}, {"id": "edge", "fg": [290, 291]}, {"id": "end_piece", "fg": [292, 293, 294, 295]}, {"id": "unconnected", "fg": 300}]}, {"id": "f_secro_fleshknot_emitter", "fg": [{"weight": 10, "sprite": 301}, {"weight": 10, "sprite": 302}, {"weight": 10, "sprite": 303}, {"weight": 10, "sprite": 304}], "animated": true}, {"id": "f_secro_flesh_bones", "fg": 305}, {"id": "f_secro_flesh_core", "fg": [{"weight": 30, "sprite": 306}, {"weight": 30, "sprite": 307}, {"weight": 30, "sprite": 308}, {"weight": 30, "sprite": 309}, {"weight": 30, "sprite": 310}], "animated": true}, {"id": "f_secro_flesh_gas_emitter", "fg": [{"weight": 10, "sprite": 311}, {"weight": 10, "sprite": 312}], "animated": true}, {"id": "f_secro_flesh_tent", "fg": 313}, {"id": "f_secro_flesh_wall", "fg": 314, "rotates": true, "multitile": true, "additional_tiles": [{"id": "center", "fg": 315}, {"id": "corner", "fg": [316, 317, 318, 319]}, {"id": "t_connection", "fg": [326, 327, 328, 329]}, {"id": "edge", "fg": [320, 321]}, {"id": "end_piece", "fg": [322, 323, 324, 325]}, {"id": "unconnected", "fg": 330}]}, {"id": "f_secro_flesh_wall_spawning", "fg": 331, "rotates": true, "multitile": true, "additional_tiles": [{"id": "center", "fg": 332}, {"id": "corner", "fg": [333, 334, 335, 336]}, {"id": "t_connection", "fg": [343, 344, 345, 346]}, {"id": "edge", "fg": [337, 338]}, {"id": "end_piece", "fg": [339, 340, 341, 342]}, {"id": "unconnected", "fg": 347}]}, {"id": "f_secro_flower_flesh", "fg": 348}, {"id": "f_secro_sack_hatch", "fg": 349}, {"id": "f_secro_tendril_cluster", "fg": 350}, {"id": "f_secro_veinstalk", "fg": 351}, {"id": "t_secro_atm_flesh", "fg": 352}, {"id": "t_secro_bars_flesh", "fg": 353}, {"id": "t_secro_brick_wall_flesh", "fg": 354, "rotates": true, "multitile": true, "additional_tiles": [{"id": "center", "fg": 355}, {"id": "corner", "fg": [356, 357, 358, 359]}, {"id": "t_connection", "fg": [366, 367, 368, 369]}, {"id": "edge", "fg": [360, 361]}, {"id": "end_piece", "fg": [362, 363, 364, 365]}, {"id": "unconnected", "fg": 370}]}, {"id": "t_secro_carpet_red_flesh", "fg": 371, "rotates": true, "multitile": true, "additional_tiles": [{"id": "center", "fg": 372}, {"id": "corner", "fg": [373, 374, 375, 376]}, {"id": "t_connection", "fg": [383, 384, 385, 386]}, {"id": "edge", "fg": [377, 378]}, {"id": "end_piece", "fg": [379, 380, 381, 382]}, {"id": "unconnected", "fg": 387}]}, {"id": "t_secro_chainfence_flesh", "fg": 388, "rotates": true, "multitile": true, "additional_tiles": [{"id": "center", "fg": 389}, {"id": "corner", "fg": [390, 391, 392, 393]}, {"id": "t_connection", "fg": [400, 401, 402, 403]}, {"id": "edge", "fg": [394, 395]}, {"id": "end_piece", "fg": [396, 397, 398, 399]}, {"id": "unconnected", "fg": 404}]}, {"id": "t_secro_chaingate_c_flesh", "fg": 405}, {"id": "t_secro_chaingate_l_flesh", "fg": 406}, {"id": "t_secro_concrete_flesh", "fg": 407, "rotates": true, "multitile": true, "additional_tiles": [{"id": "center", "fg": 408}, {"id": "corner", "fg": [409, 410, 411, 412]}, {"id": "t_connection", "fg": [419, 420, 421, 422]}, {"id": "edge", "fg": [413, 414]}, {"id": "end_piece", "fg": [415, 416, 417, 418]}, {"id": "unconnected", "fg": 423}]}, {"id": "t_secro_concrete_wall_flesh", "fg": 424, "rotates": true, "multitile": true, "additional_tiles": [{"id": "center", "fg": 425}, {"id": "corner", "fg": [426, 427, 428, 429]}, {"id": "t_connection", "fg": [436, 437, 438, 439]}, {"id": "edge", "fg": [430, 431]}, {"id": "end_piece", "fg": [432, 433, 434, 435]}, {"id": "unconnected", "fg": 440}]}, {"id": "t_secro_console_broken_flesh", "fg": 441}, {"id": "t_secro_console_flesh", "fg": 442}, {"id": "t_secro_dirt_flesh", "fg": 443, "bg": 1, "rotates": true, "multitile": true, "additional_tiles": [{"id": "center", "fg": 444, "bg": 1}, {"id": "corner", "fg": [445, 446, 447, 448], "bg": 1}, {"id": "t_connection", "fg": [455, 456, 457, 458], "bg": 1}, {"id": "edge", "fg": [449, 450], "bg": 1}, {"id": "end_piece", "fg": [451, 452, 453, 454], "bg": 1}, {"id": "unconnected", "fg": [{"weight": 3, "sprite": 459}, {"weight": 3, "sprite": 460}, {"weight": 3, "sprite": 461}, {"weight": 3, "sprite": 462}], "bg": 1}]}, {"id": "t_secro_dirt_flesh_season_winter", "fg": 443, "bg": 2, "rotates": true, "multitile": true, "additional_tiles": [{"id": "center", "fg": 444, "bg": 2}, {"id": "corner", "fg": [445, 446, 447, 448], "bg": 2}, {"id": "t_connection", "fg": [455, 456, 457, 458], "bg": 2}, {"id": "edge", "fg": [449, 450], "bg": 2}, {"id": "end_piece", "fg": [451, 452, 453, 454], "bg": 2}, {"id": "unconnected", "fg": [{"weight": 3, "sprite": 459}, {"weight": 3, "sprite": 460}, {"weight": 3, "sprite": 461}, {"weight": 3, "sprite": 462}], "bg": 2}]}, {"id": "t_secro_door_flesh", "fg": 463, "bg": 9}, {"id": "t_secro_door_glass_flesh", "fg": 464}, {"id": "t_secro_door_locked_flesh", "fg": 465, "bg": 9}, {"id": "t_secro_door_metal_flesh", "fg": 466}, {"id": "t_secro_door_metal_locked_flesh", "fg": 467}, {"id": "t_secro_experiment_vat", "fg": 468, "bg": 9}, {"id": "t_secro_fence_flesh", "fg": 469, "rotates": true, "multitile": true, "additional_tiles": [{"id": "center", "fg": 470}, {"id": "corner", "fg": [471, 472, 473, 474]}, {"id": "t_connection", "fg": [481, 482, 483, 484]}, {"id": "edge", "fg": [475, 476]}, {"id": "end_piece", "fg": [477, 478, 479, 480]}, {"id": "unconnected", "fg": 485}]}, {"id": "t_secro_flat_roof_flesh", "fg": 486, "rotates": true, "multitile": true, "additional_tiles": [{"id": "center", "fg": 487}, {"id": "corner", "fg": [488, 489, 490, 491]}, {"id": "t_connection", "fg": [498, 499, 500, 501]}, {"id": "edge", "fg": [492, 493]}, {"id": "end_piece", "fg": [494, 495, 496, 497]}, {"id": "unconnected", "fg": 502}]}, {"id": "t_secro_flesh", "fg": 503, "bg": 1, "rotates": true, "multitile": true, "additional_tiles": [{"id": "center", "fg": 504, "bg": 1}, {"id": "corner", "fg": [505, 506, 507, 508], "bg": 1}, {"id": "t_connection", "fg": [515, 516, 517, 518], "bg": 1}, {"id": "edge", "fg": [509, 510], "bg": 1}, {"id": "end_piece", "fg": [511, 512, 513, 514], "bg": 1}, {"id": "unconnected", "fg": 519, "bg": 1}]}, {"id": "t_secro_flesh_entrance_close", "fg": 520}, {"id": "t_secro_flesh_inside_up_close", "fg": 521, "bg": 1}, {"id": "t_secro_flesh_wall", "fg": 522, "bg": 1, "rotates": true, "multitile": true, "additional_tiles": [{"id": "center", "fg": 523, "bg": 1}, {"id": "corner", "fg": [524, 525, 526, 527], "bg": 1}, {"id": "t_connection", "fg": [534, 535, 536, 537], "bg": 1}, {"id": "edge", "fg": [528, 529], "bg": 1}, {"id": "end_piece", "fg": [530, 531, 532, 533], "bg": 1}, {"id": "unconnected", "fg": 538, "bg": 1}]}, {"id": "t_secro_flesh_wall_weak", "fg": 539, "bg": 1, "rotates": true, "multitile": true, "additional_tiles": [{"id": "center", "fg": 540, "bg": 503}, {"id": "corner", "fg": [541, 542, 543, 544]}, {"id": "t_connection", "fg": [551, 552, 553, 554]}, {"id": "edge", "fg": [545, 546]}, {"id": "end_piece", "fg": [547, 548, 549, 550]}, {"id": "unconnected", "fg": 555, "bg": 521}]}, {"id": "t_secro_floor_flesh", "fg": 556, "rotates": true, "multitile": true, "additional_tiles": [{"id": "center", "fg": 557}, {"id": "corner", "fg": [558, 559, 560, 561]}, {"id": "t_connection", "fg": [568, 569, 570, 571]}, {"id": "edge", "fg": [562, 563]}, {"id": "end_piece", "fg": [564, 565, 566, 567]}, {"id": "unconnected", "fg": 572}]}, {"id": "t_secro_gates_control_concrete_flesh", "fg": 573}, {"id": "t_secro_gates_mech_control_flesh", "fg": 574}, {"id": "t_secro_grass_flesh", "fg": 575, "bg": 1, "rotates": true, "multitile": true, "additional_tiles": [{"id": "center", "fg": 576, "bg": 1}, {"id": "corner", "fg": [577, 578, 579, 580], "bg": 1}, {"id": "t_connection", "fg": [587, 588, 589, 590], "bg": 1}, {"id": "edge", "fg": [581, 582], "bg": 1}, {"id": "end_piece", "fg": [583, 584, 585, 586], "bg": 1}, {"id": "unconnected", "fg": 591, "bg": 1}]}, {"id": "t_secro_grass_flesh_season_winter", "fg": 575, "bg": 2, "rotates": true, "multitile": true, "additional_tiles": [{"id": "center", "fg": 576, "bg": 2}, {"id": "corner", "fg": [577, 578, 579, 580], "bg": 2}, {"id": "t_connection", "fg": [587, 588, 589, 590], "bg": 2}, {"id": "edge", "fg": [581, 582], "bg": 2}, {"id": "end_piece", "fg": [583, 584, 585, 586], "bg": 2}, {"id": "unconnected", "fg": 591, "bg": 2}]}, {"id": "t_secro_grass_long_flesh", "fg": 592, "bg": 1, "rotates": true, "multitile": true, "additional_tiles": [{"id": "center", "fg": 593, "bg": 1}, {"id": "corner", "fg": [594, 595, 596, 597], "bg": 1}, {"id": "t_connection", "fg": [604, 605, 606, 607], "bg": 1}, {"id": "edge", "fg": [598, 599], "bg": 1}, {"id": "end_piece", "fg": [600, 601, 602, 603], "bg": 1}, {"id": "unconnected", "fg": 608, "bg": 1}]}, {"id": "t_secro_grass_long_flesh_season_winter", "fg": 592, "bg": 2, "rotates": true, "multitile": true, "additional_tiles": [{"id": "center", "fg": 593, "bg": 2}, {"id": "corner", "fg": [594, 595, 596, 597], "bg": 2}, {"id": "t_connection", "fg": [604, 605, 606, 607], "bg": 2}, {"id": "edge", "fg": [598, 599], "bg": 2}, {"id": "end_piece", "fg": [600, 601, 602, 603], "bg": 2}, {"id": "unconnected", "fg": 608, "bg": 2}]}, {"id": "t_secro_grass_tall_flesh", "fg": 609, "bg": 1, "rotates": true, "multitile": true, "additional_tiles": [{"id": "center", "fg": 610, "bg": 1}, {"id": "corner", "fg": [611, 612, 613, 614], "bg": 1}, {"id": "t_connection", "fg": [621, 622, 623, 624], "bg": 1}, {"id": "edge", "fg": [615, 616], "bg": 1}, {"id": "end_piece", "fg": [617, 618, 619, 620], "bg": 1}, {"id": "unconnected", "fg": 625, "bg": 1}]}, {"id": "t_secro_grass_tall_flesh_season_winter", "fg": 609, "bg": 2, "rotates": true, "multitile": true, "additional_tiles": [{"id": "center", "fg": 610, "bg": 2}, {"id": "corner", "fg": [611, 612, 613, 614], "bg": 2}, {"id": "t_connection", "fg": [621, 622, 623, 624], "bg": 2}, {"id": "edge", "fg": [615, 616], "bg": 2}, {"id": "end_piece", "fg": [617, 618, 619, 620], "bg": 2}, {"id": "unconnected", "fg": 625, "bg": 2}]}, {"id": "t_secro_ladder_broken_flesh", "fg": 626}, {"id": "t_secro_linoleum_gray_flesh", "fg": 627}, {"id": "t_secro_linoleum_white_flesh", "fg": 628}, {"id": "t_secro_pavement_flesh", "fg": 629, "bg": 5, "rotates": true, "multitile": true, "additional_tiles": [{"id": "center", "fg": [{"weight": 3, "sprite": 630}, {"weight": 3, "sprite": 631}, {"weight": 3, "sprite": 632}, {"weight": 3, "sprite": 633}], "bg": 5}, {"id": "corner", "fg": [{"weight": 3, "sprite": 630}, {"weight": 3, "sprite": 631}, {"weight": 3, "sprite": 632}, {"weight": 3, "sprite": 633}], "bg": 5}, {"id": "t_connection", "fg": [{"weight": 3, "sprite": 630}, {"weight": 3, "sprite": 631}, {"weight": 3, "sprite": 632}, {"weight": 3, "sprite": 633}], "bg": 5}, {"id": "edge", "fg": [{"weight": 3, "sprite": 630}, {"weight": 3, "sprite": 631}, {"weight": 3, "sprite": 632}, {"weight": 3, "sprite": 633}], "bg": 5}, {"id": "end_piece", "fg": [{"weight": 3, "sprite": 630}, {"weight": 3, "sprite": 631}, {"weight": 3, "sprite": 632}, {"weight": 3, "sprite": 633}], "bg": 5}, {"id": "unconnected", "fg": [{"weight": 3, "sprite": 634}, {"weight": 3, "sprite": 635}, {"weight": 3, "sprite": 636}, {"weight": 3, "sprite": 637}], "bg": 5}]}, {"id": "t_secro_pavement_y_flesh", "fg": 629, "bg": 638, "rotates": true, "multitile": true, "additional_tiles": [{"id": "center", "fg": [{"weight": 3, "sprite": 630}, {"weight": 3, "sprite": 631}, {"weight": 3, "sprite": 632}, {"weight": 3, "sprite": 633}], "bg": 638}, {"id": "corner", "fg": [{"weight": 3, "sprite": 630}, {"weight": 3, "sprite": 631}, {"weight": 3, "sprite": 632}, {"weight": 3, "sprite": 633}], "bg": 638}, {"id": "t_connection", "fg": [{"weight": 3, "sprite": 630}, {"weight": 3, "sprite": 631}, {"weight": 3, "sprite": 632}, {"weight": 3, "sprite": 633}], "bg": 638}, {"id": "edge", "fg": [{"weight": 3, "sprite": 630}, {"weight": 3, "sprite": 631}, {"weight": 3, "sprite": 632}, {"weight": 3, "sprite": 633}], "bg": 638}, {"id": "end_piece", "fg": [{"weight": 3, "sprite": 630}, {"weight": 3, "sprite": 631}, {"weight": 3, "sprite": 632}, {"weight": 3, "sprite": 633}], "bg": 638}, {"id": "unconnected", "fg": [{"weight": 3, "sprite": 634}, {"weight": 3, "sprite": 635}, {"weight": 3, "sprite": 636}, {"weight": 3, "sprite": 637}], "bg": 638}]}, {"id": "t_secro_railing_flesh", "fg": 639, "rotates": true, "multitile": true, "additional_tiles": [{"id": "center", "fg": 640}, {"id": "corner", "fg": [641, 642, 643, 644]}, {"id": "t_connection", "fg": [651, 652, 653, 654]}, {"id": "edge", "fg": [645, 646]}, {"id": "end_piece", "fg": [647, 648, 649, 650]}, {"id": "unconnected", "fg": 655}]}, {"id": "t_secro_reinforced_glass_flesh", "fg": 761, "rotates": true, "multitile": true, "additional_tiles": [{"id": "center", "fg": 762}, {"id": "corner", "fg": [763, 764, 765, 766]}, {"id": "t_connection", "fg": [773, 774, 775, 776]}, {"id": "edge", "fg": [767, 768]}, {"id": "end_piece", "fg": [769, 770, 771, 772]}, {"id": "unconnected", "fg": 777}]}, {"id": "t_secro_rock_floor_flesh", "fg": 629, "bg": 4, "rotates": true, "multitile": true, "additional_tiles": [{"id": "center", "fg": [{"weight": 3, "sprite": 630}, {"weight": 3, "sprite": 631}, {"weight": 3, "sprite": 632}, {"weight": 3, "sprite": 633}], "bg": 4}, {"id": "corner", "fg": [{"weight": 3, "sprite": 630}, {"weight": 3, "sprite": 631}, {"weight": 3, "sprite": 632}, {"weight": 3, "sprite": 633}], "bg": 4}, {"id": "t_connection", "fg": [{"weight": 3, "sprite": 630}, {"weight": 3, "sprite": 631}, {"weight": 3, "sprite": 632}, {"weight": 3, "sprite": 633}], "bg": 4}, {"id": "edge", "fg": [{"weight": 3, "sprite": 630}, {"weight": 3, "sprite": 631}, {"weight": 3, "sprite": 632}, {"weight": 3, "sprite": 633}], "bg": 4}, {"id": "end_piece", "fg": [{"weight": 3, "sprite": 630}, {"weight": 3, "sprite": 631}, {"weight": 3, "sprite": 632}, {"weight": 3, "sprite": 633}], "bg": 4}, {"id": "unconnected", "fg": [{"weight": 3, "sprite": 634}, {"weight": 3, "sprite": 635}, {"weight": 3, "sprite": 636}, {"weight": 3, "sprite": 637}], "bg": 4}]}, {"id": "t_secro_rock_wall_flesh", "fg": 656, "rotates": true, "multitile": true, "additional_tiles": [{"id": "center", "fg": 657}, {"id": "corner", "fg": [658, 659, 660, 661]}, {"id": "t_connection", "fg": [668, 669, 670, 671]}, {"id": "edge", "fg": [662, 663]}, {"id": "end_piece", "fg": [664, 665, 666, 667]}, {"id": "unconnected", "fg": 672}]}, {"id": "t_secro_shrub_flesh", "fg": 673, "bg": 1, "rotates": true, "multitile": true, "additional_tiles": [{"id": "center", "fg": 674, "bg": 1}, {"id": "corner", "fg": [675, 676, 677, 678], "bg": 1}, {"id": "t_connection", "fg": [685, 686, 687, 688], "bg": 1}, {"id": "edge", "fg": [679, 680], "bg": 1}, {"id": "end_piece", "fg": [681, 682, 683, 684], "bg": 1}, {"id": "unconnected", "fg": 689, "bg": 1}]}, {"id": "t_secro_shrub_flesh_season_winter", "fg": 673, "bg": 2, "rotates": true, "multitile": true, "additional_tiles": [{"id": "center", "fg": 674, "bg": 2}, {"id": "corner", "fg": [675, 676, 677, 678], "bg": 2}, {"id": "t_connection", "fg": [685, 686, 687, 688], "bg": 2}, {"id": "edge", "fg": [679, 680], "bg": 2}, {"id": "end_piece", "fg": [681, 682, 683, 684], "bg": 2}, {"id": "unconnected", "fg": 689, "bg": 2}]}, {"id": "t_secro_sidewalk_flesh", "fg": 690, "rotates": true, "multitile": true, "additional_tiles": [{"id": "center", "fg": 691}, {"id": "corner", "fg": [692, 693, 694, 695]}, {"id": "t_connection", "fg": [702, 703, 704, 705]}, {"id": "edge", "fg": [696, 697]}, {"id": "end_piece", "fg": [698, 699, 700, 701]}, {"id": "unconnected", "fg": 706}]}, {"id": "t_secro_stairs_broken_flesh", "fg": 707}, {"id": "t_secro_stairs_down_flesh", "fg": 708, "bg": 9}, {"id": "t_secro_stairs_up_flesh", "fg": 709, "bg": 9}, {"id": "t_secro_thconc_floor_flesh", "fg": 710, "rotates": true, "multitile": true, "additional_tiles": [{"id": "center", "fg": 711}, {"id": "corner", "fg": [712, 713, 714, 715]}, {"id": "t_connection", "fg": [722, 723, 724, 725]}, {"id": "edge", "fg": [716, 717]}, {"id": "end_piece", "fg": [718, 719, 720, 721]}, {"id": "unconnected", "fg": 726}]}, {"id": "t_secro_wall_b_flesh", "fg": 727, "rotates": true, "multitile": true, "additional_tiles": [{"id": "center", "fg": 728}, {"id": "corner", "fg": [729, 730, 731, 732]}, {"id": "t_connection", "fg": [739, 740, 741, 742]}, {"id": "edge", "fg": [733, 734]}, {"id": "end_piece", "fg": [735, 736, 737, 738]}, {"id": "unconnected", "fg": 743}]}, {"id": "t_secro_wall_flesh", "fg": 744, "rotates": true, "multitile": true, "additional_tiles": [{"id": "center", "fg": 745}, {"id": "corner", "fg": [746, 747, 748, 749]}, {"id": "t_connection", "fg": [756, 757, 758, 759]}, {"id": "edge", "fg": [750, 751]}, {"id": "end_piece", "fg": [752, 753, 754, 755]}, {"id": "unconnected", "fg": 760}]}, {"id": "t_secro_wall_glass_flesh", "fg": 761, "rotates": true, "multitile": true, "additional_tiles": [{"id": "center", "fg": 762}, {"id": "corner", "fg": [763, 764, 765, 766]}, {"id": "t_connection", "fg": [773, 774, 775, 776]}, {"id": "edge", "fg": [767, 768]}, {"id": "end_piece", "fg": [769, 770, 771, 772]}, {"id": "unconnected", "fg": 777}]}, {"id": "t_secro_wall_g_flesh", "fg": 778, "rotates": true, "multitile": true, "additional_tiles": [{"id": "center", "fg": 779}, {"id": "corner", "fg": [780, 781, 782, 783]}, {"id": "t_connection", "fg": [790, 791, 792, 793]}, {"id": "edge", "fg": [784, 785]}, {"id": "end_piece", "fg": [786, 787, 788, 789]}, {"id": "unconnected", "fg": 794}]}, {"id": "t_secro_wall_metal_flesh", "fg": 795, "rotates": false, "multitile": true, "additional_tiles": [{"id": "center", "fg": 796}, {"id": "corner", "fg": [797, 798, 799, 800]}, {"id": "t_connection", "fg": [807, 808, 809, 810]}, {"id": "edge", "fg": [801, 802]}, {"id": "end_piece", "fg": [803, 804, 805, 806]}, {"id": "unconnected", "fg": 811}]}, {"id": "t_secro_wall_r_flesh", "fg": 812, "rotates": true, "multitile": true, "additional_tiles": [{"id": "center", "fg": 813}, {"id": "corner", "fg": [814, 815, 816, 817]}, {"id": "t_connection", "fg": [824, 825, 826, 827]}, {"id": "edge", "fg": [818, 819]}, {"id": "end_piece", "fg": [820, 821, 822, 823]}, {"id": "unconnected", "fg": 828}]}, {"id": "t_secro_wall_w_flesh", "fg": 829, "rotates": true, "multitile": true, "additional_tiles": [{"id": "center", "fg": 830}, {"id": "corner", "fg": [831, 832, 833, 834]}, {"id": "t_connection", "fg": [841, 842, 843, 844]}, {"id": "edge", "fg": [835, 836]}, {"id": "end_piece", "fg": [837, 838, 839, 840]}, {"id": "unconnected", "fg": 845}]}, {"id": "t_secro_water_dispenser_flesh", "fg": 846}, {"id": "t_secro_window_bars_flesh", "fg": 847}, {"id": "t_secro_window_flesh", "fg": 848, "bg": 9}, {"id": "t_secro_window_frame_flesh", "fg": 849, "bg": 9}, {"id": "mon_shifter", "fg": 850, "bg": 9}, {"id": "corpse_mon_shifter", "fg": 851, "bg": 9}, {"id": "mon_shifter_zombie", "fg": 852, "bg": 9}, {"id": "mon_shifter_zombie_rot", "fg": 853, "bg": 9}, {"id": "mon_fleshweaver", "fg": 854}, {"id": "corpse_mon_fleshweaver", "fg": 855}, {"id": "mon_bot_secrolauncher", "fg": 856, "bg": 9}, {"id": "mon_bot_secromissile", "fg": 857, "bg": 9}, {"id": "mon_bot_secroriflewalker", "fg": 858, "bg": 9}, {"id": "mon_bot_secroshocker", "fg": 859}, {"id": "mon_secro_electurret", "fg": [{"weight": 10, "sprite": 860}, {"weight": 10, "sprite": 861}, {"weight": 10, "sprite": 860}, {"weight": 10, "sprite": 861}, {"weight": 10, "sprite": 860}, {"weight": 10, "sprite": 861}, {"weight": 10, "sprite": 862}, {"weight": 10, "sprite": 863}, {"weight": 10, "sprite": 862}, {"weight": 10, "sprite": 863}, {"weight": 10, "sprite": 862}, {"weight": 10, "sprite": 863}], "bg": 9, "animated": true, "rotates": false}, {"id": "mon_secro_gravturret", "fg": [{"weight": 10, "sprite": 864}, {"weight": 10, "sprite": 865}, {"weight": 10, "sprite": 864}, {"weight": 10, "sprite": 865}, {"weight": 10, "sprite": 864}, {"weight": 10, "sprite": 865}, {"weight": 10, "sprite": 866}, {"weight": 10, "sprite": 867}, {"weight": 10, "sprite": 866}, {"weight": 10, "sprite": 867}, {"weight": 10, "sprite": 866}, {"weight": 10, "sprite": 867}], "bg": 9, "animated": true, "rotates": false}, {"id": "mon_secro_laserturret", "fg": [{"weight": 10, "sprite": 868}, {"weight": 10, "sprite": 869}, {"weight": 10, "sprite": 868}, {"weight": 10, "sprite": 869}, {"weight": 10, "sprite": 868}, {"weight": 10, "sprite": 869}, {"weight": 10, "sprite": 870}, {"weight": 10, "sprite": 871}, {"weight": 10, "sprite": 870}, {"weight": 10, "sprite": 871}, {"weight": 10, "sprite": 870}, {"weight": 10, "sprite": 871}], "bg": 9, "animated": true, "rotates": false}, {"id": "mon_secro_laserturret_mod", "fg": [{"weight": 10, "sprite": 868}, {"weight": 10, "sprite": 869}, {"weight": 10, "sprite": 868}, {"weight": 10, "sprite": 869}, {"weight": 10, "sprite": 868}, {"weight": 10, "sprite": 869}, {"weight": 10, "sprite": 870}, {"weight": 10, "sprite": 871}, {"weight": 10, "sprite": 870}, {"weight": 10, "sprite": 871}, {"weight": 10, "sprite": 870}, {"weight": 10, "sprite": 871}], "bg": 9, "animated": true, "rotates": false}, {"id": "bot_secroinforcer", "fg": 872}, {"id": "bot_secrolauncher", "fg": 873}, {"id": "bot_secromissile", "fg": 874}, {"id": "bot_secroriflewalker", "fg": 875}, {"id": "bot_secroshocker", "fg": 876}, {"id": "flesh_sack_death", "fg": 877}, {"id": "flesh_taken_death", "fg": 878}, {"id": "relinquish_revive", "fg": 879}, {"id": "saddler_brute_detach", "fg": 880}, {"id": "saddler_detach", "fg": 881}, {"id": "saddler_scout_detach", "fg": 882}, {"id": "shifter_shift", "fg": 883, "bg": 9}, {"id": "SSimpactgrenade", "fg": 884}, {"id": "SSimpactgrenadeact", "fg": 885}, {"id": "SSxgrenade", "fg": 886}, {"id": "SSxgrenadeact", "fg": 887}, {"id": "SSygrenade", "fg": 888}, {"id": "SSygrenadeact", "fg": 889}, {"id": "SSzgrenade", "fg": 890}, {"id": "SSzgrenadeact", "fg": 891}, {"id": "overlay_effect_pedo_restraint", "fg": 892}, {"id": "overlay_effect_rooty_grasp", "fg": 893}, {"id": "overlay_effect_secro_akin_siphon_ally", "fg": 894}, {"id": "overlay_effect_secro_akin_siphon_foe", "fg": 895}, {"id": "overlay_effect_secro_cordev_corrupt", "fg": 896}, {"id": "overlay_effect_secro_mawy_web", "fg": 897}, {"id": "overlay_effect_secro_uruxis_shroud", "fg": 898}, {"id": "overlay_effect_unify_bloodslow", "fg": 899}, {"id": "overlay_effect_vector_infect", "fg": 900}, {"id": "laser_rifle_secrodragon", "fg": 901}, {"id": "squirtler_bulb", "fg": 902}, {"id": "SS_grenade_launchersecrodragon", "fg": 903}, {"id": "SS_pershield", "fg": 904}, {"id": "clinger_clinging", "fg": 905}, {"id": "overlay_worn_clinger_clinging", "fg": 906}, {"id": "sflesh_bio", "fg": 907}, {"id": "sflesh_bio_cooked", "fg": 908}, {"id": "sflesh_bio_smoked", "fg": 909}, {"id": "mon_insect_saddler", "fg": 910, "bg": 9}, {"id": "corpse_mon_insect_saddler", "fg": 911}, {"id": "mon_insect_saddler_baby", "fg": 912, "bg": 9}, {"id": "corpse_mon_insect_saddler_baby", "fg": 913}, {"id": "mon_insect_saddler_baby_potent", "fg": 914, "bg": 9}, {"id": "corpse_mon_insect_saddler_baby_potent", "fg": 915}, {"id": "mon_insect_saddler_brood", "fg": 916, "bg": 9}, {"id": "corpse_mon_insect_saddler_brood", "fg": 917}, {"id": "mon_insect_saddler_brute", "fg": 918, "bg": 9}, {"id": "corpse_mon_insect_saddler_brute", "fg": 919}, {"id": "mon_insect_saddler_scout", "fg": 920, "bg": 9}, {"id": "corpse_mon_insect_saddler_scout", "fg": 921}, {"id": "mon_saddler_infected", "fg": 922, "bg": 9}, {"id": "corpse_mon_saddler_infected", "fg": 923}, {"id": "mon_zombie_saddler_infected", "fg": 924, "bg": 9}, {"id": "corpse_mon_zombie_saddler_infected", "fg": 925}, {"id": "mon_zombie_saddler_used", "fg": 926, "bg": 9}, {"id": "corpse_mon_zombie_saddler_used", "fg": 927}, {"id": "mon_zombieworm_noxeater", "fg": 928}, {"id": "corpse_mon_zombieworm_noxeater", "fg": 929}, {"id": "mon_insect_parasiteworm_int", "fg": 930}, {"id": "mon_insect_parasiteworm_move", "fg": 931}, {"id": "mon_insect_parasiteworm_pain", "fg": 932}, {"id": "mon_insect_parasiteworm_stomach", "fg": 933}, {"id": "mon_unknown_unknown", "fg": 934}, {"id": "mon_unknown_unknown_carrion", "fg": 935}, {"id": "mon_unknown_unknown_vector", "fg": 936}, {"id": "mon_vector_spore", "fg": 937, "bg": 9}, {"id": "mon_vector_sprig", "fg": 938, "bg": 9}, {"id": "corpse_mon_vector_sprig", "fg": 939}, {"id": "mon_vector_sprout", "fg": 940, "bg": 9}, {"id": "corpse_mon_vector_sprout", "fg": 941}, {"id": "mon_zombie_skittyweavy", "fg": 942, "bg": 9}, {"id": "corpse_mon_zombie_skittyweavy", "fg": 943}, {"id": "mon_zombie_skittyweavy_repleshy", "fg": 944, "bg": 9}, {"id": "corpse_mon_zombie_skittyweavy_repleshy", "fg": 945}, {"id": "mon_zombie_skittyweavy_sickly", "fg": 946, "bg": 9}, {"id": "corpse_mon_zombie_skittyweavy_sickly", "fg": 947}, {"id": "mon_zombie_blade", "fg": 948, "bg": 9}, {"id": "corpse_mon_zombie_blade", "fg": 949}, {"id": "mon_zombie_razor", "fg": 950, "bg": 9}, {"id": "corpse_mon_zombie_razor", "fg": 951}, {"id": "mon_zombie_serratedblade", "fg": 952, "bg": 9}, {"id": "corpse_mon_zombie_serratedblade", "fg": 953}, {"id": "mon_zombie_sharpblade", "fg": 954, "bg": 9}, {"id": "corpse_mon_zombie_sharpblade", "fg": 955}, {"id": "mon_zedbow_axxuros", "fg": 956, "bg": 9}, {"id": "corpse_mon_zedbow_axxuros", "fg": 957}, {"id": "mon_zedbow_axxuros_armed", "fg": 958, "bg": 9}, {"id": "corpse_mon_zedbow_axxuros_armed", "fg": 959}, {"id": "mon_zedbow_exios", "fg": 960, "bg": 9}, {"id": "corpse_mon_zedbow_exios", "fg": 961}, {"id": "mon_zedbow_exios_armed", "fg": 962, "bg": 9}, {"id": "corpse_mon_zedbow_exios_armed", "fg": 963}, {"id": "mon_zedbow_kaxix", "fg": 964, "bg": 9}, {"id": "corpse_mon_zedbow_kaxix", "fg": 965}, {"id": "mon_zedbow_kaxix_armed", "fg": 966, "bg": 9}, {"id": "corpse_mon_zedbow_kaxix_armed", "fg": 967}, {"id": "mon_zedfail_chomp", "fg": 968, "bg": 9}, {"id": "corpse_mon_zedfail_chomp", "fg": 969}, {"id": "mon_zedfail_floral", "fg": 970, "bg": 9}, {"id": "corpse_mon_zedfail_floral", "fg": 971}, {"id": "mon_zedfail_seeker", "fg": 972, "bg": 9}, {"id": "corpse_mon_zedfail_seeker", "fg": 973}, {"id": "mon_zedfail_squirtler", "fg": 974}, {"id": "corpse_mon_zedfail_squirtler", "fg": 975}, {"id": "mon_zedfail_twistcrawl", "fg": 976, "bg": 9}, {"id": "corpse_mon_zedfail_twistcrawl", "fg": 977}, {"id": "mon_sflesh_fleshling_big", "fg": 978, "bg": 9}, {"id": "mon_sflesh_fleshling_med", "fg": 979, "bg": 9}, {"id": "mon_sflesh_fleshling_smol", "fg": 980, "bg": 9}, {"id": "mon_sflesh_fleshling_tiny", "fg": 981, "bg": 9}, {"id": "mon_sflesh_jaw", "fg": [{"weight": 30, "sprite": 982}, {"weight": 30, "sprite": 983}, {"weight": 3, "sprite": 984}], "animated": true}, {"id": "corpse_mon_sflesh_parasyte", "fg": 985}, {"id": "mon_sflesh_sack", "fg": 986}, {"id": "mon_sflesh_surface_spawner", "fg": [{"weight": 300, "sprite": 987}, {"weight": 300, "sprite": 988}, {"weight": 30, "sprite": 989}, {"weight": 3, "sprite": 990}, {"weight": 3, "sprite": 991}], "animated": true}, {"id": "mon_sflesh_tendril", "fg": 992}, {"id": "mon_sflesh_veinstalk_crawly", "fg": [{"weight": 10, "sprite": 993}, {"weight": 10, "sprite": 994}, {"weight": 10, "sprite": 995}], "animated": true}, {"id": "mon_sflesh_beaver", "fg": 996, "bg": 9, "rotates": false}, {"id": "corpse_mon_sflesh_beaver", "fg": 997, "rotates": false}, {"id": "mon_sflesh_cat", "fg": 998, "bg": 9, "rotates": false}, {"id": "corpse_mon_sflesh_cat", "fg": 999, "rotates": false}, {"id": "mon_sflesh_cat_kitten", "fg": 1000, "bg": 8}, {"id": "corpse_mon_sflesh_cat_kitten", "fg": 1001}, {"id": "mon_sflesh_chipmunk", "fg": 1002, "bg": 9, "rotates": false}, {"id": "corpse_mon_sflesh_chipmunk", "fg": 1003, "rotates": false}, {"id": "mon_sflesh_cow", "fg": 1004, "bg": 9, "rotates": false}, {"id": "corpse_mon_sflesh_cow", "fg": 1005, "rotates": false}, {"id": "mon_sflesh_coyote", "fg": 1006, "bg": 9, "rotates": false}, {"id": "corpse_mon_sflesh_coyote", "fg": 1007, "rotates": false}, {"id": "mon_sflesh_deer", "fg": 1008, "bg": 9, "rotates": false}, {"id": "corpse_mon_sflesh_deer", "fg": 1009, "rotates": false}, {"id": "mon_sflesh_dog", "fg": 1010, "rotates": false}, {"id": "corpse_mon_sflesh_dog", "fg": 1011, "rotates": false}, {"id": "mon_sflesh_dog_pup", "fg": 1012, "bg": 9, "rotates": false}, {"id": "corpse_mon_sflesh_dog_pup", "fg": 1013, "rotates": false}, {"id": "mon_sflesh_fox", "fg": 1014, "bg": 9, "rotates": false}, {"id": "corpse_mon_sflesh_fox", "fg": 1015, "rotates": false}, {"id": "mon_sflesh_groundhog", "fg": 1016, "bg": 9, "rotates": false}, {"id": "corpse_mon_sflesh_groundhog", "fg": 1017, "rotates": false}, {"id": "mon_sflesh_horse", "fg": 1018, "bg": 9, "rotates": false}, {"id": "corpse_mon_sflesh_horse", "fg": 1019, "rotates": false}, {"id": "mon_sflesh_lemming", "fg": 1020, "bg": 9, "rotates": false}, {"id": "corpse_mon_sflesh_lemming", "fg": 1021, "rotates": false}, {"id": "mon_sflesh_mink", "fg": 1022, "bg": 9, "rotates": false}, {"id": "corpse_mon_sflesh_mink", "fg": 1023, "rotates": false}, {"id": "mon_sflesh_muskrat", "fg": 1024, "bg": 9, "rotates": false}, {"id": "corpse_mon_sflesh_muskrat", "fg": 1025, "rotates": false}, {"id": "mon_sflesh_opossum", "fg": 1026, "bg": 6, "rotates": false}, {"id": "corpse_mon_sflesh_opossum", "fg": 1027, "rotates": false}, {"id": "mon_sflesh_otter", "fg": 1028, "bg": 7, "rotates": false}, {"id": "corpse_mon_sflesh_otter", "fg": 1029, "rotates": false}, {"id": "mon_sflesh_pig", "fg": 1030, "bg": 9, "rotates": false}, {"id": "corpse_mon_sflesh_pig", "fg": 1031, "rotates": false}, {"id": "mon_sflesh_rabbit", "fg": 1032, "bg": 6, "rotates": false}, {"id": "corpse_mon_sflesh_rabbit", "fg": 1033, "rotates": false}, {"id": "mon_sflesh_raccoon", "fg": 1034, "bg": 9, "rotates": false}, {"id": "corpse_mon_sflesh_raccoon", "fg": 1035, "rotates": false}, {"id": "mon_sflesh_sheep", "fg": 1036, "bg": 9, "rotates": false}, {"id": "corpse_mon_sflesh_sheep", "fg": 1037, "rotates": false}, {"id": "mon_sflesh_squirrel", "fg": 1038, "bg": 8, "rotates": false}, {"id": "corpse_mon_sflesh_squirrel", "fg": 1039, "rotates": false}, {"id": "mon_sflesh_taken_bear", "fg": 1040, "bg": 9}, {"id": "corpse_mon_sflesh_taken_bear", "fg": 1041}, {"id": "mon_sflesh_taken_cougar", "fg": 1042, "bg": 9}, {"id": "corpse_mon_sflesh_taken_cougar", "fg": 1043}, {"id": "mon_sflesh_taken_moose", "fg": 1044, "bg": 9}, {"id": "corpse_mon_sflesh_taken_moose", "fg": 1045}, {"id": "mon_sflesh_taken_rat", "fg": 1046, "bg": 9}, {"id": "corpse_mon_sflesh_taken_rat", "fg": 1047}, {"id": "mon_sflesh_weasel", "fg": 1048, "bg": 6, "rotates": false}, {"id": "corpse_mon_sflesh_weasel", "fg": 1049, "rotates": false}, {"id": "mon_sflesh_wolf", "fg": 1050, "bg": 9, "rotates": false}, {"id": "corpse_mon_sflesh_wolf", "fg": 1051, "rotates": false}, {"id": "mon_sflesh_boomer", "fg": 1052, "bg": 9, "rotates": false}, {"id": "mon_sflesh_dog_skeleton", "fg": 1053, "bg": 9}, {"id": "corpse_mon_sflesh_dog_skeleton", "fg": 1054}, {"id": "mon_sflesh_dog_zombie_cop", "fg": 1055, "bg": 9}, {"id": "corpse_mon_sflesh_dog_zombie_cop", "fg": 1056}, {"id": "mon_sflesh_dog_zombie_rot", "fg": 1057, "bg": 9}, {"id": "corpse_mon_sflesh_dog_zombie_rot", "fg": 1058}, {"id": "mon_sflesh_skeleton", "fg": 1059, "bg": 9}, {"id": "corpse_mon_sflesh_skeleton", "fg": 1060}, {"id": "mon_sflesh_skeleton_brute", "fg": 1061, "bg": 9}, {"id": "corpse_mon_sflesh_skeleton_brute", "fg": 1062}, {"id": "mon_sflesh_taken_zombie", "fg": [{"weight": 3, "sprite": 1063}, {"weight": 3, "sprite": 1064}, {"weight": 3, "sprite": 1065}, {"weight": 3, "sprite": 1066}], "bg": 9}, {"id": "corpse_mon_sflesh_taken_zombie", "fg": 1067}, {"id": "mon_sflesh_zombie_acidic", "fg": 1068, "bg": 9, "rotates": false}, {"id": "corpse_mon_sflesh_zombie_acidic", "fg": 1069, "rotates": false}, {"id": "mon_sflesh_zombie_anklebiter", "fg": [{"weight": 3, "sprite": 1070}, {"weight": 3, "sprite": 1071}, {"weight": 3, "sprite": 1072}, {"weight": 3, "sprite": 1073}], "bg": 9}, {"id": "corpse_mon_sflesh_zombie_anklebiter", "fg": 1074}, {"id": "mon_sflesh_zombie_biter", "fg": 1075, "bg": 9}, {"id": "corpse_mon_sflesh_zombie_biter", "fg": 1076}, {"id": "mon_sflesh_zombie_brainless", "fg": 1077, "bg": 9}, {"id": "corpse_mon_sflesh_zombie_brainless", "fg": 1078}, {"id": "mon_sflesh_zombie_brute", "fg": 1079, "bg": 9}, {"id": "corpse_mon_sflesh_zombie_brute", "fg": 1080}, {"id": "mon_sflesh_zombie_brute_grappler", "fg": 1081, "bg": 9}, {"id": "corpse_mon_sflesh_zombie_brute_grappler", "fg": 1082}, {"id": "mon_sflesh_zombie_brute_ninja", "fg": 1083, "bg": 9}, {"id": "corpse_mon_sflesh_zombie_brute_ninja", "fg": 1084}, {"id": "corpse_mon_sflesh_zombie_brute_shocker", "fg": 1085, "rotates": false}, {"id": "mon_sflesh_zombie_child", "fg": [{"weight": 3, "sprite": 1086}, {"weight": 3, "sprite": 1087}, {"weight": 3, "sprite": 1088}, {"weight": 3, "sprite": 1089}], "bg": 9}, {"id": "corpse_mon_sflesh_zombie_child", "fg": 1090}, {"id": "mon_sflesh_zombie_crawler", "fg": 1091, "bg": 9}, {"id": "corpse_mon_sflesh_zombie_crawler", "fg": 1092}, {"id": "mon_sflesh_zombie_creepy", "fg": [{"weight": 3, "sprite": 1093}, {"weight": 3, "sprite": 1094}, {"weight": 3, "sprite": 1095}, {"weight": 3, "sprite": 1096}], "bg": 9}, {"id": "corpse_mon_sflesh_zombie_creepy", "fg": 1097}, {"id": "mon_sflesh_zombie_dog", "fg": 1098, "bg": 9}, {"id": "corpse_mon_sflesh_zombie_dog", "fg": 1099}, {"id": "mon_sflesh_zombie_ears", "fg": 1100, "bg": 9}, {"id": "corpse_mon_sflesh_zombie_ears", "fg": 1101}, {"id": "corpse_mon_sflesh_zombie_electric", "fg": 1102, "rotates": false}, {"id": "mon_sflesh_zombie_fat", "fg": [{"weight": 3, "sprite": 1103}, {"weight": 3, "sprite": 1104}, {"weight": 3, "sprite": 1105}, {"weight": 3, "sprite": 1106}], "bg": 9}, {"id": "corpse_mon_sflesh_zombie_fat", "fg": 1107}, {"id": "mon_sflesh_zombie_gasbag", "fg": 1108, "bg": 9, "rotates": false}, {"id": "mon_sflesh_zombie_grappler", "fg": 1109, "bg": 9}, {"id": "corpse_mon_sflesh_zombie_grappler", "fg": 1110}, {"id": "mon_sflesh_zombie_hollow", "fg": 1111, "bg": 9}, {"id": "corpse_mon_sflesh_zombie_hollow", "fg": 1112}, {"id": "mon_sflesh_zombie_hunter", "fg": 1113, "bg": 9, "rotates": false}, {"id": "corpse_mon_sflesh_zombie_hunter", "fg": 1114, "bg": 9, "rotates": false}, {"id": "mon_sflesh_zombie_mancroc", "fg": 1115, "bg": 9, "rotates": false}, {"id": "corpse_mon_sflesh_zombie_mancroc", "fg": 1116, "rotates": false}, {"id": "mon_sflesh_zombie_master", "fg": 1117, "bg": 9, "rotates": false}, {"id": "corpse_mon_sflesh_zombie_master", "fg": 1118, "rotates": false}, {"id": "mon_sflesh_zombie_necro", "fg": 1119, "bg": 9, "rotates": false}, {"id": "corpse_mon_sflesh_zombie_necro", "fg": 1120, "rotates": false}, {"id": "corpse_mon_sflesh_zombie_nullfield", "fg": 1121, "rotates": false}, {"id": "mon_sflesh_zombie_predator", "fg": 1122, "bg": 9, "rotates": false}, {"id": "corpse_mon_sflesh_zombie_predator", "fg": 1123, "rotates": false}, {"id": "mon_sflesh_zombie_screecher", "fg": 1124, "bg": 9, "rotates": false}, {"id": "corpse_mon_zombie_screecher", "fg": 1125, "rotates": false}, {"id": "mon_sflesh_zombie_shriekling", "fg": [{"weight": 3, "sprite": 1126}, {"weight": 3, "sprite": 1127}, {"weight": 3, "sprite": 1128}, {"weight": 3, "sprite": 1129}], "bg": 9}, {"id": "corpse_mon_sflesh_zombie_shriekling", "fg": 1130}, {"id": "mon_sflesh_zombie_skull", "fg": 1131, "bg": 9}, {"id": "corpse_mon_sflesh_zombie_skull", "fg": 1132}, {"id": "mon_sflesh_zombie_smoker", "fg": 1133, "bg": 9, "rotates": false}, {"id": "mon_sflesh_zombie_snotgobbler", "fg": 1134, "bg": 9}, {"id": "mon_sflesh_zombie_soldier", "fg": 1135, "bg": 9}, {"id": "corpse_mon_sflesh_zombie_soldier", "fg": 1136}, {"id": "mon_sflesh_zombie_spitter", "fg": 1137, "bg": 9}, {"id": "corpse_mon_sflesh_zombie_spitter", "fg": 1138}, {"id": "mon_sflesh_zombie_sproglodyte", "fg": 1139, "rotates": false}, {"id": "corpse_mon_sflesh_zombie_sproglodyte", "fg": 1140, "rotates": false}, {"id": "mon_sflesh_zombie_survivor", "fg": 1141, "bg": 9}, {"id": "corpse_mon_sflesh_zombie_survivor", "fg": 1142}, {"id": "mon_sflesh_zombie_thorny", "fg": 1143, "bg": 9, "rotates": false}, {"id": "corpse_mon_sflesh_zombie_thorny", "fg": 1144, "rotates": false}, {"id": "mon_sflesh_zombie_tough", "fg": [{"weight": 3, "sprite": 1145}, {"weight": 3, "sprite": 1146}, {"weight": 3, "sprite": 1147}, {"weight": 3, "sprite": 1148}], "bg": 9}, {"id": "corpse_mon_sflesh_zombie_tough", "fg": 1149}, {"id": "mon_sflesh_zombie_waif", "fg": 1150, "bg": 9, "rotates": false}, {"id": "corpse_mon_sflesh_zombie_waif", "fg": 1151, "rotates": false}, {"id": "mon_zombie_grubby", "fg": 1152, "bg": 9}, {"id": "corpse_mon_zombie_grubby", "fg": 1153}, {"id": "mon_zombie_slimy", "fg": 1154, "bg": 9}, {"id": "corpse_mon_zombie_slimy", "fg": 1155}, {"id": "mon_zombie_lick", "fg": 1156, "bg": 9}, {"id": "corpse_mon_zombie_lick", "fg": 1157}, {"id": "mon_zombie_mlick", "fg": 1158, "bg": 9}, {"id": "corpse_mon_zombie_mlick", "fg": 1159}, {"id": "mon_zombie_xlick", "fg": 1160, "bg": 9}, {"id": "corpse_mon_zombie_xlick", "fg": 1161}, {"id": "mon_zombie_nightwail_shadow", "fg": 1162}, {"id": "mon_zombie_WALKINGPOTATO", "fg": 1163, "bg": 9}, {"id": "corpse_mon_zombie_WALKINGPOTATO", "fg": 1164}, {"id": "mon_zombie_zawk", "fg": 1165, "bg": 9}, {"id": "corpse_mon_zombie_zawk", "fg": 1166}, {"id": "mon_zombie_zoth", "fg": 1167, "bg": 9}, {"id": "corpse_mon_zombie_zoth", "fg": 1168}, {"id": "mon_zombie_cling", "fg": 1169, "bg": 9}, {"id": "mon_zombie_disser", "fg": 1170, "bg": 9}, {"id": "corpse_mon_zombie_disser", "fg": 1171}, {"id": "mon_zombie_equinox_necros", "fg": 1172, "bg": 9}, {"id": "mon_zombie_equinox_necros_cut", "fg": 1173, "bg": 9}, {"id": "mon_zombie_equinox_necros_emit", "fg": 1174, "bg": 9}, {"id": "mon_zombie_equinox_necros_stab", "fg": 1175, "bg": 9}, {"id": "mon_zombie_fake_ichorus", "fg": 1176, "bg": 9}, {"id": "mon_zombie_fake_psyrus", "fg": 1177, "bg": 9}, {"id": "corpse_mon_zombie_jolt", "fg": 1178}, {"id": "mon_zombie_jolt_bolt_big", "fg": 1179}, {"id": "mon_zombie_jolt_bolt_smol", "fg": 1180}, {"id": "mon_zombie_nautilus", "fg": 1181}, {"id": "corpse_mon_zombie_nautilus", "fg": 1182}, {"id": "mon_zombie_nautilus_pedo", "fg": 1183}, {"id": "mon_zombie_nix", "fg": 1184, "bg": 9}, {"id": "corpse_mon_zombie_nix", "fg": 1185}, {"id": "corpse_mon_zombie_nocturne", "fg": 1186}, {"id": "mon_zombie_relinquish", "fg": 1187, "bg": 9}, {"id": "mon_zombie_relinquish_revived", "fg": 1188, "bg": 9}, {"id": "corpse_mon_zombie_relinquish_revived", "fg": 1189}, {"id": "mon_zombie_stray", "fg": 1190, "bg": 9}, {"id": "corpse_mon_zombie_stray", "fg": 1191}, {"id": "mon_zombie_stray_w_acid_mode", "fg": 1192, "bg": 9}, {"id": "corpse_mon_zombie_stray_w_acid_mode", "fg": 1193}, {"id": "mon_zombie_stray_w_acid_stro1", "fg": 1194, "bg": 9}, {"id": "corpse_mon_zombie_stray_w_acid_stro1", "fg": 1195}, {"id": "mon_zombie_stray_w_acid_stro2", "fg": 1196, "bg": 9}, {"id": "corpse_mon_zombie_stray_w_acid_stro2", "fg": 1197}, {"id": "mon_zombie_stray_w_acid_stro3", "fg": 1198, "bg": 9}, {"id": "corpse_mon_zombie_stray_w_acid_stro3", "fg": 1199}, {"id": "mon_zombie_stray_w_acid_weak", "fg": 1200, "bg": 9}, {"id": "corpse_mon_zombie_stray_w_acid_weak", "fg": 1201}, {"id": "mon_zombie_stray_w_leaf_mode", "fg": 1202, "bg": 9}, {"id": "corpse_mon_zombie_stray_w_leaf_mode", "fg": 1203}, {"id": "mon_zombie_stray_w_leaf_stro1", "fg": 1204, "bg": 9}, {"id": "corpse_mon_zombie_stray_w_leaf_stro1", "fg": 1205}, {"id": "mon_zombie_stray_w_leaf_stro2", "fg": 1206, "bg": 9}, {"id": "corpse_mon_zombie_stray_w_leaf_stro2", "fg": 1207}, {"id": "mon_zombie_stray_w_leaf_stro3", "fg": 1208, "bg": 9}, {"id": "corpse_mon_zombie_stray_w_leaf_stro3", "fg": 1209}, {"id": "mon_zombie_stray_w_leaf_stro3_triffid", "fg": 1210, "bg": 9}, {"id": "corpse_mon_zombie_stray_w_leaf_stro3_triffid", "fg": 1211}, {"id": "mon_zombie_stray_w_leaf_weak", "fg": 1212, "bg": 9}, {"id": "corpse_mon_zombie_stray_w_leaf_weak", "fg": 1213}, {"id": "mon_zombie_uruxis", "fg": 1214, "bg": 9}, {"id": "corpse_mon_zombie_uruxis", "fg": 1215}, {"id": "mon_zombie_bellymouth", "fg": 1216, "bg": 9}, {"id": "corpse_mon_zombie_bellymouth", "fg": 1217}, {"id": "mon_zombie_mouth", "fg": 1218, "bg": 9}, {"id": "corpse_mon_zombie_mouth", "fg": 1219}, {"id": "mon_zombie_omouth", "fg": 1220, "bg": 9}, {"id": "corpse_mon_zombie_omouth", "fg": 1221}, {"id": "mon_zombie_suctionmouth", "fg": 1222, "bg": 9}, {"id": "corpse_mon_zombie_suctionmouth", "fg": 1223}, {"id": "mon_zombie_revenant", "fg": 1224, "bg": 9}, {"id": "corpse_mon_zombie_revenant", "fg": 1225}, {"id": "mon_zombie_revenant_allure", "fg": 1226, "bg": 9}, {"id": "corpse_mon_zombie_revenant_allure", "fg": 1227}, {"id": "mon_zombie_revenant_forsaken", "fg": 1228, "bg": 9}, {"id": "corpse_mon_zombie_revenant_forsaken", "fg": 1229}, {"id": "mon_zombie_defile", "fg": 1230, "bg": 9}, {"id": "corpse_mon_zombie_defile", "fg": 1231}, {"id": "mon_zombie_leptiosa", "fg": 1232, "bg": 9}, {"id": "corpse_mon_zombie_leptiosa", "fg": 1233}, {"id": "mon_zombie_scourge", "fg": 1234, "bg": 9}, {"id": "corpse_mon_zombie_scourge", "fg": 1235}, {"id": "mon_zombie_arachnia", "fg": 1236, "bg": 9}, {"id": "corpse_mon_zombie_arachnia", "fg": 1237}, {"id": "mon_zombie_spoder", "fg": 1238, "bg": 9}, {"id": "corpse_mon_zombie_spoder", "fg": 1239}, {"id": "mon_zombie_spoderhug", "fg": 1240, "bg": 9}, {"id": "corpse_mon_zombie_spoderhug", "fg": 1241}, {"id": "mon_zombie_spodertickle", "fg": 1242, "bg": 9}, {"id": "corpse_mon_zombie_spodertickle", "fg": 1243}, {"id": "mon_zombie_swarmer_evo_hungry", "fg": 1244, "bg": 9}, {"id": "corpse_mon_zombie_swarmer_evo_hungry", "fg": 1245}, {"id": "mon_zombie_swarmer_evo_savage", "fg": 1246, "bg": 9}, {"id": "corpse_mon_zombie_swarmer_evo_savage", "fg": 1247}, {"id": "mon_zombie_swarmer_evo_starving", "fg": 1248, "bg": 9}, {"id": "corpse_mon_zombie_swarmer_evo_starving", "fg": 1249}, {"id": "mon_zombie_swarmer_evo_virulent", "fg": 1250, "bg": 9}, {"id": "corpse_mon_zombie_swarmer_evo_virulent", "fg": 1251}, {"id": "mon_zombie_swarmer_moderate", "fg": [{"weight": 3, "sprite": 1252}, {"weight": 3, "sprite": 1255}, {"weight": 3, "sprite": 1256}, {"weight": 3, "sprite": 1257}, {"weight": 3, "sprite": 1258}, {"weight": 3, "sprite": 1259}, {"weight": 3, "sprite": 1260}, {"weight": 3, "sprite": 1261}, {"weight": 3, "sprite": 1262}, {"weight": 3, "sprite": 1253}, {"weight": 3, "sprite": 1254}], "bg": 9}, {"id": "corpse_mon_zombie_swarmer_moderate", "fg": 1263}, {"id": "mon_zombie_swarmer_segway", "fg": [{"weight": 3, "sprite": 1264}, {"weight": 3, "sprite": 1267}, {"weight": 3, "sprite": 1268}, {"weight": 3, "sprite": 1269}, {"weight": 3, "sprite": 1270}, {"weight": 3, "sprite": 1271}, {"weight": 3, "sprite": 1272}, {"weight": 3, "sprite": 1273}, {"weight": 3, "sprite": 1274}, {"weight": 3, "sprite": 1265}, {"weight": 3, "sprite": 1266}], "bg": 9}, {"id": "corpse_mon_zombie_swarmer_segway", "fg": 1275}, {"id": "mon_zombie_swarmer_strong", "fg": [{"weight": 3, "sprite": 1276}, {"weight": 3, "sprite": 1279}, {"weight": 3, "sprite": 1280}, {"weight": 3, "sprite": 1281}, {"weight": 3, "sprite": 1282}, {"weight": 3, "sprite": 1283}, {"weight": 3, "sprite": 1284}, {"weight": 3, "sprite": 1285}, {"weight": 3, "sprite": 1286}, {"weight": 3, "sprite": 1277}, {"weight": 3, "sprite": 1278}], "bg": 9}, {"id": "corpse_mon_zombie_swarmer_strong", "fg": 1287}, {"id": "mon_zombie_swarmer_weak", "fg": [{"weight": 3, "sprite": 1288}, {"weight": 3, "sprite": 1291}, {"weight": 3, "sprite": 1292}, {"weight": 3, "sprite": 1293}, {"weight": 3, "sprite": 1294}, {"weight": 3, "sprite": 1295}, {"weight": 3, "sprite": 1296}, {"weight": 3, "sprite": 1297}, {"weight": 3, "sprite": 1298}, {"weight": 3, "sprite": 1289}, {"weight": 3, "sprite": 1290}], "bg": 9}, {"id": "corpse_mon_zombie_swarmer_weak", "fg": 1299}, {"id": "mon_zombie_tendricles", "fg": 1300, "bg": 9}, {"id": "corpse_mon_zombie_tendricles", "fg": 1301}, {"id": "mon_zombie_tendrils", "fg": 1302, "bg": 9}, {"id": "corpse_mon_zombie_tendrils", "fg": 1303}, {"id": "mon_zombie_tentawraith_tent", "fg": 1304}, {"id": "mon_zombie_thicktendrils", "fg": 1305, "bg": 9}, {"id": "corpse_mon_zombie_thicktendrils", "fg": 1306}, {"id": "mon_zombie_pellucid", "fg": 1307, "bg": 9}, {"id": "corpse_mon_zombie_pellucid", "fg": 1308}, {"id": "mon_zombie_translucent", "fg": 1309, "bg": 9}, {"id": "corpse_mon_zombie_translucent", "fg": 1310}, {"id": "mon_zombie_bloodvessel", "fg": 1311, "bg": 9}, {"id": "corpse_mon_zombie_bloodvessel", "fg": 1312}, {"id": "mon_zombie_unify", "fg": 1313, "bg": 9}, {"id": "corpse_mon_zombie_unify", "fg": 1314}, {"id": "mon_zombie_unity", "fg": 1315, "bg": 9}, {"id": "corpse_mon_zombie_unity", "fg": 1316}], "//": "range 1 to 1328", "sprite_width": 32, "sprite_height": 32, "sprite_offset_x": 0, "sprite_offset_y": 0}, {"file": "secronom_normal_offset.png", "tiles": [{"id": "overlay_effect_omi_curse", "bg": 1329}, {"id": "overlay_effect_parasiteworm_int", "bg": 1330}, {"id": "overlay_effect_parasiteworm_move", "bg": 1331}, {"id": "overlay_effect_parasiteworm_pain", "bg": 1332}, {"id": "overlay_effect_parasiteworm_stomach", "bg": 1333}, {"id": "overlay_effect_secro_dissed", "bg": 1334}, {"id": "overlay_effect_secro_fleshysnaky_enrage", "bg": 1335}, {"id": "overlay_effect_secro_flesh_tree_grab", "bg": 1336}, {"id": "overlay_effect_secro_gorepit_wall_dmg", "bg": 1337}, {"id": "overlay_effect_secro_necros_para", "bg": 1338}, {"id": "overlay_effect_secro_nix_fear", "bg": 1339}], "//": "range 1329 to 1344", "sprite_width": 32, "sprite_height": 32, "sprite_offset_x": 0, "sprite_offset_y": -16}, {"file": "secronom_large.png", "tiles": [{"id": "bg_big_normal_shaddow", "fg": 1345}, {"id": "bg_secro_growth", "fg": 1346}, {"id": "bg_secro_growth_winter", "fg": 1347}, {"id": "bg_shadow_large", "fg": 1348}, {"id": "bg_shadow_normal2", "fg": 1349}, {"id": "bg_vector_growth", "fg": 1350}, {"id": "bg_vector_growth_winter", "fg": 1351}, {"id": "t_ladder", "fg": 1352}, {"id": "t_secro_metal_hatch_o", "fg": 1353}, {"id": "t_tree_vector", "fg": 1354, "bg": 1350}, {"id": "t_tree_vector_season_winter", "fg": 1355, "bg": 1351}, {"id": "f_secro_boulder_large_flesh", "fg": 1356}, {"id": "f_secro_tree_flesh_atk", "fg": 1357}, {"id": "t_secro_column_flesh", "fg": 1358, "rotates": false}, {"id": "t_secro_flesh_entrance_open", "fg": 1359}, {"id": "t_secro_flesh_entrance_up", "fg": 1360}, {"id": "t_secro_flesh_inside_down", "fg": 1361}, {"id": "t_secro_flesh_inside_up", "fg": 1362}, {"id": "t_secro_gutter_downspout_flesh", "fg": 1363}, {"id": "t_secro_tree_flesh", "fg": 1364, "bg": 1346}, {"id": "t_secro_tree_flesh_season_winter", "fg": 1364, "bg": 1347}, {"id": "t_secro_tree_young_flesh", "fg": 1365, "bg": 1346}, {"id": "t_secro_tree_young_flesh_season_winter", "fg": 1365, "bg": 1347}, {"id": "veinhole_gap", "fg": 1366}, {"id": "veinhole_gap_act", "fg": 1367}, {"id": "mon_ayenel", "fg": 1368, "bg": 1349}, {"id": "corpse_mon_ayenel", "fg": 1369, "bg": 1349}, {"id": "mon_maneater", "fg": 1370, "bg": 1349}, {"id": "corpse_mon_maneater", "fg": 1371, "bg": 1349}, {"id": "mon_secrodragon_sleep", "fg": 1372, "bg": 1348}, {"id": "corpse_mon_secrodragon_sleep", "fg": 1373, "bg": 1348}, {"id": "mon_secrodragon_woke", "fg": 1374, "bg": 1348}, {"id": "corpse_mon_secrodragon_woke", "fg": 1375, "bg": 1348}, {"id": "mon_bot_secroinforcer", "fg": 1376}, {"id": "mon_saddler_infected_brute", "fg": 1377, "bg": 1349}, {"id": "corpse_mon_saddler_infected_brute", "fg": 1378, "bg": 1349}, {"id": "mon_saddler_infected_scout", "fg": 1379, "bg": 1349}, {"id": "corpse_mon_saddler_infected_scout", "fg": 1380}, {"id": "mon_zombie_saddler_brute_used", "fg": 1381, "bg": 1349}, {"id": "corpse_mon_zombie_saddler_brute_used", "fg": 1382, "bg": 1349}, {"id": "mon_zombie_saddler_infected_brute", "fg": 1383, "bg": 1349}, {"id": "mon_zombie_saddler_infected_scout", "fg": 1384, "bg": 1349}, {"id": "corpse_mon_zombie_saddler_infected_scout", "fg": 1385, "bg": 1349}, {"id": "mon_zombie_saddler_scout_used", "fg": 1386, "bg": 1349}, {"id": "corpse_mon_zombie_saddler_scout_used", "fg": 1387}, {"id": "mon_zombieworm_gravedigger", "fg": 1388, "bg": 1348}, {"id": "corpse_mon_zombieworm_gravedigger", "fg": 1389}, {"id": "mon_zombieworm_mawy", "fg": 1390, "bg": 1348}, {"id": "corpse_mon_zombieworm_mawy", "fg": 1391, "bg": 1348}, {"id": "mon_zombieworm_wriggly", "fg": 1392}, {"id": "corpse_mon_zombieworm_wriggly", "fg": 1393}, {"id": "mon_carrion", "fg": 1394}, {"id": "corpse_mon_carrion", "fg": 1395}, {"id": "mon_carrion_alpha", "fg": 1396}, {"id": "corpse_mon_carrion_alpha", "fg": 1397}, {"id": "mon_carrion_dismantler", "fg": 1398}, {"id": "corpse_mon_carrion_dismantler", "fg": 1399}, {"id": "mon_carrion_orifice", "fg": 1400}, {"id": "corpse_mon_carrion_orifice", "fg": 1401}, {"id": "mon_vector", "fg": 1402}, {"id": "corpse_mon_vector", "fg": 1403}, {"id": "mon_vector_seedler", "fg": 1404}, {"id": "corpse_mon_vector_seedler", "fg": 1405}, {"id": "mon_vector_stinger", "fg": 1406}, {"id": "corpse_mon_vector_stinger", "fg": 1407}, {"id": "mon_vector_tree", "fg": 1408}, {"id": "corpse_mon_vector_tree", "fg": 1409}, {"id": "mon_zedbow_drexx", "fg": 1410, "bg": 1349}, {"id": "corpse_mon_zedbow_drexx", "fg": 1411}, {"id": "mon_zedbow_drexx_armed", "fg": 1412, "bg": 1349}, {"id": "corpse_mon_zedbow_drexx_armed", "fg": 1413}, {"id": "mon_zedbow_epixo", "fg": 1414, "bg": 1348}, {"id": "corpse_mon_zedbow_epixo", "fg": 1415}, {"id": "mon_zedbow_epixo_armed", "fg": 1416, "bg": 1348}, {"id": "corpse_mon_zedbow_epixo_armed", "fg": 1417}, {"id": "mon_zombie_charger", "fg": 1418, "bg": 1349}, {"id": "corpse_mon_zombie_charger", "fg": 1419}, {"id": "mon_zombie_charger_plate", "fg": 1420, "bg": 1349}, {"id": "corpse_mon_zombie_charger_plate", "fg": 1421}, {"id": "mon_zombie_charger_spike", "fg": 1422, "bg": 1349}, {"id": "corpse_mon_zombie_charger_spike", "fg": 1423}, {"id": "mon_zombie_charger_vanguard", "fg": 1424, "bg": 1348}, {"id": "corpse_mon_zombie_charger_vanguard", "fg": 1425}, {"id": "mon_sflesh_entrance", "fg": 1426}, {"id": "mon_sflesh_flesh", "fg": 1427, "bg": 1348}, {"id": "mon_sflesh_fleshling_huge", "fg": 1428, "bg": 1348}, {"id": "mon_sflesh_flesh_city", "fg": 1429}, {"id": "mon_sflesh_flesh_wall", "fg": 1430, "bg": 1348}, {"id": "mon_sflesh_flesh_wall_city", "fg": 1431}, {"id": "mon_sflesh_flesh_weak", "fg": 1432}, {"id": "mon_sflesh_parasyte", "fg": 1433}, {"id": "mon_sflesh_taken", "fg": 1434}, {"id": "mon_sflesh_taken_potent", "fg": 1435}, {"id": "mon_sflesh_vbeast", "fg": 1436, "bg": 1348}, {"id": "mon_sflesh_veinstalk", "fg": [{"weight": 20, "sprite": 1437}, {"weight": 40, "sprite": 1438}, {"weight": 20, "sprite": 1439}], "animated": true}, {"id": "mon_sflesh_vrumbler", "fg": 1440, "bg": 1348}, {"id": "mon_sflesh_zombie_turret", "fg": 1441}, {"id": "mon_sflesh_nakedmolerat_giant", "fg": 1442, "rotates": false}, {"id": "corpse_mon_sflesh_nakedmolerat_giant", "fg": 1443, "rotates": false}, {"id": "mon_sflesh_boomer_huge", "fg": 1444}, {"id": "mon_sflesh_skeleton_hulk", "fg": 1445}, {"id": "corpse_mon_sflesh_skeleton_hulk", "fg": 1446}, {"id": "mon_sflesh_zombie_brute_shocker", "fg": [{"weight": 10, "sprite": 1447}, {"weight": 10, "sprite": 1448}, {"weight": 10, "sprite": 1449}, {"weight": 10, "sprite": 1450}], "bg": 1345, "animated": true, "rotates": false}, {"id": "mon_sflesh_zombie_corrosive", "fg": 1451, "rotates": false}, {"id": "corpse_mon_sflesh_zombie_corrosive", "fg": 1452, "rotates": false}, {"id": "mon_sflesh_zombie_electric", "fg": [{"weight": 10, "sprite": 1453}, {"weight": 10, "sprite": 1454}, {"weight": 10, "sprite": 1455}, {"weight": 10, "sprite": 1456}], "bg": 1345, "animated": true, "rotates": false}, {"id": "mon_sflesh_zombie_hulk", "fg": 1457}, {"id": "corpse_mon_sflesh_zombie_hulk", "fg": 1458}, {"id": "mon_sflesh_zombie_nullfield", "fg": [{"weight": 10, "sprite": 1459}, {"weight": 10, "sprite": 1460}, {"weight": 10, "sprite": 1461}, {"weight": 10, "sprite": 1462}, {"weight": 10, "sprite": 1463}, {"weight": 10, "sprite": 1464}], "bg": 1345, "animated": true, "rotates": false}, {"id": "mon_sflesh_zombie_static", "fg": [{"weight": 25, "sprite": 1465}, {"weight": 25, "sprite": 1466}, {"weight": 25, "sprite": 1467}, {"weight": 25, "sprite": 1468}], "animated": true, "bg": 1345, "rotates": false}, {"id": "corpse_mon_sflesh_zombie_static", "fg": 1469, "rotates": false}, {"id": "mon_zombie_glut", "fg": 1470, "bg": 1348}, {"id": "corpse_mon_zombie_glut", "fg": 1471}, {"id": "mon_zombie_nightwail", "fg": 1472, "bg": 1348}, {"id": "mon_zombie_akin", "fg": 1473, "bg": 1349}, {"id": "corpse_mon_zombie_akin", "fg": 1474}, {"id": "mon_zombie_cordev", "fg": 1475}, {"id": "corpse_mon_zombie_cordev", "fg": 1476}, {"id": "mon_zombie_equinox", "fg": 1477}, {"id": "mon_zombie_fleshknot_mode", "fg": 1478}, {"id": "mon_zombie_fleshknot_stro", "fg": 1479}, {"id": "mon_zombie_fleshknot_vstro", "fg": 1480}, {"id": "mon_zombie_fleshknot_weak", "fg": 1481}, {"id": "mon_zombie_fleshmonger", "fg": 1482, "bg": 1348}, {"id": "mon_zombie_fleshysnaky", "fg": 1483, "bg": 1348}, {"id": "mon_zombie_gorepit", "fg": 1484}, {"id": "mon_zombie_gorepit_tent", "fg": 1485}, {"id": "mon_zombie_ichorus", "fg": 1486, "bg": 1349}, {"id": "corpse_mon_zombie_ichorus", "fg": 1487}, {"id": "mon_zombie_jolt", "fg": [{"weight": 10, "sprite": 1488}, {"weight": 10, "sprite": 1489}, {"weight": 10, "sprite": 1490}], "bg": 1349, "animated": true}, {"id": "mon_zombie_nocturne", "fg": 1491, "bg": 1349}, {"id": "mon_zombie_psyrus", "fg": 1492, "bg": 1348}, {"id": "corpse_mon_zombie_psyrus", "fg": 1493}, {"id": "mon_zombie_tentawraith", "fg": 1494}, {"id": "corpse_mon_zombie_tentawraith", "fg": 1495}, {"id": "mon_zombie_blacktitan", "fg": 1496, "bg": 1348}, {"id": "corpse_mon_zombie_blacktitan", "fg": 1497}, {"id": "mon_zombie_titan", "fg": 1498, "bg": 1348}, {"id": "corpse_mon_zombie_titan", "fg": 1499}, {"id": "mon_zombie_bloodfiend", "fg": 1500, "bg": 1348}, {"id": "corpse_mon_zombie_bloodfiend", "fg": 1501}, {"id": "mon_zombie_hemo", "fg": 1502, "bg": 1348}, {"id": "corpse_mon_zombie_hemo", "fg": 1503}, {"id": "overlay_mutation_SECRONOM_FLESH_BIO", "fg": 1504, "bg": 1348}], "//": "range 1345 to 1520", "sprite_width": 64, "sprite_height": 80, "sprite_offset_x": -16, "sprite_offset_y": -48}]}]