{"id": "t_carpet_base", "fg": ["13074_t_carpet_base_0"], "bg": ["9190_bg_t_floor_0"], "rotates": false, "multitile": true, "additional_tiles": [{"id": "center", "fg": ["13075_t_carpet_base_2"], "bg": ["9190_bg_t_floor_0"]}, {"id": "corner", "fg": ["13076_t_carpet_base_3", "13077_t_carpet_base_4", "13078_t_carpet_base_5", "13079_t_carpet_base_6"], "bg": ["9190_bg_t_floor_0"]}, {"id": "t_connection", "fg": ["13086_t_carpet_base_7", "13087_t_carpet_base_8", "13088_t_carpet_base_9", "13089_t_carpet_base_10"], "bg": ["9190_bg_t_floor_0"]}, {"id": "edge", "fg": ["13080_t_carpet_base_11", "13081_t_carpet_base_12"], "bg": ["9190_bg_t_floor_0"]}, {"id": "end_piece", "fg": ["13082_t_carpet_base_13", "13083_t_carpet_base_14", "13084_t_carpet_base_15", "13085_t_carpet_base_16"], "bg": ["9190_bg_t_floor_0"]}, {"id": "unconnected", "fg": ["13090_t_carpet_base_17"], "bg": ["9190_bg_t_floor_0"]}]}