{"id": "t_chickenwire_fence", "fg": ["12671_t_chickenwire_fence_0"], "rotates": false, "multitile": true, "additional_tiles": [{"id": "center", "fg": ["12672_t_chickenwire_fence_1"], "bg": ["9162_bg_pavement_0"]}, {"id": "corner", "fg": ["12673_t_chickenwire_fence_3", "12674_t_chickenwire_fence_4", "12675_t_chickenwire_fence_5", "12676_t_chickenwire_fence_6"], "bg": ["9162_bg_pavement_0"]}, {"id": "t_connection", "fg": ["12683_t_chickenwire_fence_7", "12684_t_chickenwire_fence_8", "12685_t_chickenwire_fence_9", "12686_t_chickenwire_fence_10"], "bg": ["9162_bg_pavement_0"]}, {"id": "edge", "fg": ["12677_t_chickenwire_fence_11", "12678_t_chickenwire_fence_12"], "bg": ["9162_bg_pavement_0"]}, {"id": "end_piece", "fg": ["12679_t_chickenwire_fence_13", "12680_t_chickenwire_fence_14", "12681_t_chickenwire_fence_15", "12682_t_chickenwire_fence_16"], "bg": ["9162_bg_pavement_0"]}, {"id": "unconnected", "fg": ["12687_t_chickenwire_fence_17"], "bg": ["9162_bg_pavement_0"]}], "bg": []}