{"id": "t_junk_wall", "fg": ["15931_t_junk_wall_0"], "rotates": false, "multitile": true, "additional_tiles": [{"id": "center", "fg": ["15932_t_junk_wall_1"], "bg": ["13367_t_junk_floor_0"]}, {"id": "corner", "fg": ["15933_t_junk_wall_3", "15934_t_junk_wall_4", "15935_t_junk_wall_5", "15936_t_junk_wall_6"], "bg": ["13367_t_junk_floor_0"]}, {"id": "t_connection", "fg": ["15943_t_junk_wall_7", "15944_t_junk_wall_8", "15945_t_junk_wall_9", "15946_t_junk_wall_10"], "bg": ["13367_t_junk_floor_0"]}, {"id": "edge", "fg": ["15937_t_junk_wall_11", "15938_t_junk_wall_12"], "bg": ["13367_t_junk_floor_0"]}, {"id": "end_piece", "fg": ["15939_t_junk_wall_13", "15940_t_junk_wall_14", "15941_t_junk_wall_15", "15942_t_junk_wall_16"], "bg": ["13367_t_junk_floor_0"]}, {"id": "unconnected", "fg": ["15947_t_junk_wall_17"], "bg": ["13367_t_junk_floor_0"]}], "bg": []}