{"id": "t_wall_y", "fg": ["16642_t_wall_y_0"], "rotates": false, "multitile": true, "additional_tiles": [{"id": "center", "fg": ["16643_t_wall_y_1"], "bg": []}, {"id": "corner", "fg": ["16644_t_wall_y_2", "16645_t_wall_y_3", "16646_t_wall_y_4", "16647_t_wall_y_5"], "bg": []}, {"id": "t_connection", "fg": ["16654_t_wall_y_6", "16655_t_wall_y_7", "16656_t_wall_y_8", "16657_t_wall_y_9"], "bg": []}, {"id": "edge", "fg": ["16648_t_wall_y_10", "16649_t_wall_y_11"], "bg": []}, {"id": "end_piece", "fg": ["16650_t_wall_y_12", "16651_t_wall_y_13", "16652_t_wall_y_14", "16653_t_wall_y_15"], "bg": []}, {"id": "unconnected", "fg": ["16658_t_wall_y_16"], "bg": []}], "bg": []}