{"id": "t_wall_wood_chipped", "fg": ["16625_t_wall_wood_chipped_0"], "bg": ["9131_bg_dirt_0"], "rotates": true, "multitile": true, "additional_tiles": [{"id": "center", "fg": ["16626_t_wall_wood_chipped_2"], "bg": ["9131_bg_dirt_0"]}, {"id": "corner", "fg": ["16627_t_wall_wood_chipped_3", "16628_t_wall_wood_chipped_4", "16629_t_wall_wood_chipped_5", "16630_t_wall_wood_chipped_6"], "bg": ["9131_bg_dirt_0"]}, {"id": "t_connection", "fg": ["16637_t_wall_wood_chipped_7", "16638_t_wall_wood_chipped_8", "16639_t_wall_wood_chipped_9", "16640_t_wall_wood_chipped_10"], "bg": ["9131_bg_dirt_0"]}, {"id": "edge", "fg": ["16631_t_wall_wood_chipped_11", "16632_t_wall_wood_chipped_12"], "bg": ["9131_bg_dirt_0"]}, {"id": "end_piece", "fg": ["16633_t_wall_wood_chipped_13", "16634_t_wall_wood_chipped_14", "16635_t_wall_wood_chipped_15", "16636_t_wall_wood_chipped_16"], "bg": ["9131_bg_dirt_0"]}, {"id": "unconnected", "fg": ["16641_t_wall_wood_chipped_17"], "bg": ["9131_bg_dirt_0"]}]}