{"id": "f_plant_seed", "fg": ["11302_f_plant_seed_0"], "rotates": true, "multitile": true, "additional_tiles": [{"id": "center", "fg": ["11303_f_plant_seed_1"], "bg": []}, {"id": "corner", "fg": ["11304_f_plant_seed_2", "11305_f_plant_seed_3", "11306_f_plant_seed_4", "11307_f_plant_seed_5"], "bg": []}, {"id": "t_connection", "fg": ["11314_f_plant_seed_6", "11315_f_plant_seed_7", "11316_f_plant_seed_8", "11317_f_plant_seed_9"], "bg": []}, {"id": "edge", "fg": ["11308_f_plant_seed_10", "11309_f_plant_seed_11"], "bg": []}, {"id": "end_piece", "fg": ["11310_f_plant_seed_12", "11311_f_plant_seed_13", "11312_f_plant_seed_14", "11313_f_plant_seed_15"], "bg": []}, {"id": "unconnected", "fg": ["11318_f_plant_seed_16", "11318_f_plant_seed_16"], "bg": []}], "bg": []}