{"id": "mon_feral_human_pipe", "fg": [{"weight": 10, "sprite": "7443_mon_feral_human_pipe_0"}, {"weight": 10, "sprite": "7445_mon_feral_human_pipe_1"}, {"weight": 10, "sprite": "7446_mon_feral_human_pipe_2"}, {"weight": 10, "sprite": "7447_mon_feral_human_pipe_3"}, {"weight": 10, "sprite": "7448_mon_feral_human_pipe_4"}, {"weight": 10, "sprite": "7449_mon_feral_human_pipe_5"}, {"weight": 10, "sprite": "7450_mon_feral_human_pipe_6"}, {"weight": 10, "sprite": "7451_mon_feral_human_pipe_7"}, {"weight": 10, "sprite": "7452_mon_feral_human_pipe_8"}, {"weight": 10, "sprite": "7444_mon_feral_human_pipe_9"}], "bg": ["9173_bot_grocerybot_1"], "rotates": false, "animated": false}